erlab_coat/__init__.py
erlab_coat/meta.py
erlab_coat/plots.py
erlab_coat/preprocessing.py
erlab_coat/statistics.py
erlab_coat/twitter.py
erlab_coat-0.0.0.dist-info/METADATA
erlab_coat-0.0.0.dist-info/WHEEL
erlab_coat-0.0.0.dist-info/top_level.txt
erlab_coat-0.0.0.dist-info/RECORD
